{
  "article_id": "62bd3cd7-ead8-4351-ae13-ced984e42bb9",
  "source": "yfinance",
  "ticker": "MSFT",
  "title": "Dan Ives Says ‘Market Is Mispricing’ MSFT Stock — Here’s Why",
  "url": "https://stocktwits.com/news-articles/markets/equity/why-dan-ives-says-market-is-mispricing-microsoft-stock/cZ00hf9ReDl",
  "published_at": null,
  "processed_at": "2026-06-03T04:58:46.422842",
  "sentences": [
    "Dan Ives Says ‘Market Is Mispricing’ MSFT Stock — Here’s Why Wedbush’s Dan Ives stays bullish on Microsoft, Alphabet and the broader AI trade, calling current market sentiment an underestimation of the next phase of Big Tech growth."
  ],
  "entities": [
    {
      "entity": "We",
      "raw_text": "We",
      "label": "ORG",
      "start_char": 61,
      "end_char": 63,
      "sentence_idx": 0,
      "context_window": "Dan Ives Says ‘Market Is Mispricing’ MSFT Stock — Here’s Why Wedbush’s Dan Ives stays bullish on Microsoft, Alphabet and the broader AI trade, calling current market sentiment an underestimation of the next phase of Big Tech growth.",
      "sentiment_label": "negative",
      "sentiment_score": 0.8009496331214905,
      "positive_score": 0.02658245898783207,
      "negative_score": 0.8009496331214905,
      "neutral_score": 0.17246796190738678
    },
    {
      "entity": "Microsoft",
      "raw_text": "Microsoft",
      "label": "ORG",
      "start_char": 97,
      "end_char": 106,
      "sentence_idx": 0,
      "context_window": "Dan Ives Says ‘Market Is Mispricing’ MSFT Stock — Here’s Why Wedbush’s Dan Ives stays bullish on Microsoft, Alphabet and the broader AI trade, calling current market sentiment an underestimation of the next phase of Big Tech growth.",
      "sentiment_label": "negative",
      "sentiment_score": 0.8009496331214905,
      "positive_score": 0.02658245898783207,
      "negative_score": 0.8009496331214905,
      "neutral_score": 0.17246796190738678
    },
    {
      "entity": "Alphabet",
      "raw_text": "Alphabet",
      "label": "ORG",
      "start_char": 108,
      "end_char": 116,
      "sentence_idx": 0,
      "context_window": "Dan Ives Says ‘Market Is Mispricing’ MSFT Stock — Here’s Why Wedbush’s Dan Ives stays bullish on Microsoft, Alphabet and the broader AI trade, calling current market sentiment an underestimation of the next phase of Big Tech growth.",
      "sentiment_label": "negative",
      "sentiment_score": 0.8009496331214905,
      "positive_score": 0.02658245898783207,
      "negative_score": 0.8009496331214905,
      "neutral_score": 0.17246796190738678
    },
    {
      "entity": "Big Tech",
      "raw_text": "Big Tech",
      "label": "ORG",
      "start_char": 216,
      "end_char": 224,
      "sentence_idx": 0,
      "context_window": "Dan Ives Says ‘Market Is Mispricing’ MSFT Stock — Here’s Why Wedbush’s Dan Ives stays bullish on Microsoft, Alphabet and the broader AI trade, calling current market sentiment an underestimation of the next phase of Big Tech growth.",
      "sentiment_label": "negative",
      "sentiment_score": 0.8009496331214905,
      "positive_score": 0.02658245898783207,
      "negative_score": 0.8009496331214905,
      "neutral_score": 0.17246796190738678
    }
  ],
  "article_sentiment_label": "negative",
  "article_sentiment_score": 0.8009,
  "company_sentiments": {
    "We": {
      "label": "negative",
      "score": 0.8009496331214905,
      "positive_score": 0.0266,
      "negative_score": 0.8009,
      "neutral_score": 0.1725,
      "mentions": 1
    },
    "Microsoft": {
      "label": "negative",
      "score": 0.8009496331214905,
      "positive_score": 0.0266,
      "negative_score": 0.8009,
      "neutral_score": 0.1725,
      "mentions": 1
    },
    "Alphabet": {
      "label": "negative",
      "score": 0.8009496331214905,
      "positive_score": 0.0266,
      "negative_score": 0.8009,
      "neutral_score": 0.1725,
      "mentions": 1
    },
    "Big Tech": {
      "label": "negative",
      "score": 0.8009496331214905,
      "positive_score": 0.0266,
      "negative_score": 0.8009,
      "neutral_score": 0.1725,
      "mentions": 1
    }
  },
  "embedding_id": "99db3ef3-7a66-436b-a01c-5272f07a6af0"
}