{
  "article_id": "8b405440-6af3-47eb-81b6-d9c9fbd22197",
  "source": "alphavantage",
  "ticker": "AAPL,MSFT,TSLA,NVDA",
  "title": "Apple Inc. $AAPL Shares Acquired by Solidarity Wealth LLC",
  "url": "https://www.marketbeat.com/instant-alerts/filing-apple-inc-aapl-shares-acquired-by-solidarity-wealth-llc-2026-02-03/",
  "published_at": "2026-02-03T08:22:40Z",
  "processed_at": "2026-06-03T04:58:31.742222",
  "sentences": [
    "Apple Inc. $AAPL Shares Acquired by Solidarity Wealth LLC Solidarity Wealth LLC has increased its stake in Apple Inc.",
    "($AAPL) by 2.1%, making it their largest holding.",
    "This comes as Apple exceeded Q1 earnings expectations, driven by strong iPhone 17 demand, and announced a quarterly dividend of $0.26 per share.",
    "Various other institutional investors have also adjusted their positions in AAPL, while analysts have reiterated \"buy\" ratings and raised price targets for the stock."
  ],
  "entities": [
    {
      "entity": "Apple",
      "raw_text": "Apple Inc",
      "label": "ORG",
      "start_char": 0,
      "end_char": 9,
      "sentence_idx": 0,
      "context_window": "Apple Inc. $AAPL Shares Acquired by Solidarity Wealth LLC Solidarity Wealth LLC has increased its stake in Apple Inc. ($AAPL) by 2.1%, making it their largest holding. This comes as Apple exceeded Q1 earnings expectations, driven by strong iPhone 17 demand, and announced a quarterly dividend of $0.26 per share.",
      "sentiment_label": "positive",
      "sentiment_score": 0.9546487331390381,
      "positive_score": 0.9546487331390381,
      "negative_score": 0.01815214194357395,
      "neutral_score": 0.02719918265938759
    },
    {
      "entity": "Solidarity Wealth",
      "raw_text": "Solidarity Wealth LLC",
      "label": "ORG",
      "start_char": 36,
      "end_char": 57,
      "sentence_idx": 0,
      "context_window": "Apple Inc. $AAPL Shares Acquired by Solidarity Wealth LLC Solidarity Wealth LLC has increased its stake in Apple Inc. ($AAPL) by 2.1%, making it their largest holding. This comes as Apple exceeded Q1 earnings expectations, driven by strong iPhone 17 demand, and announced a quarterly dividend of $0.26 per share.",
      "sentiment_label": "positive",
      "sentiment_score": 0.9546487331390381,
      "positive_score": 0.9546487331390381,
      "negative_score": 0.01815214194357395,
      "neutral_score": 0.02719918265938759
    },
    {
      "entity": "Apple",
      "raw_text": "Apple",
      "label": "ORG",
      "start_char": 182,
      "end_char": 187,
      "sentence_idx": 2,
      "context_window": "Apple Inc. $AAPL Shares Acquired by Solidarity Wealth LLC Solidarity Wealth LLC has increased its stake in Apple Inc. ($AAPL) by 2.1%, making it their largest holding. This comes as Apple exceeded Q1 earnings expectations, driven by strong iPhone 17 demand, and announced a quarterly dividend of $0.26 per share. Various other institutional investors have also adjusted their positions in AAPL, while analysts have reiterated \"buy\" ratings and raised price targets for the stock.",
      "sentiment_label": "positive",
      "sentiment_score": 0.9525806307792664,
      "positive_score": 0.9525806307792664,
      "negative_score": 0.01751033589243889,
      "neutral_score": 0.02990908920764923
    },
    {
      "entity": "Aa",
      "raw_text": "AA",
      "label": "ORG",
      "start_char": 389,
      "end_char": 391,
      "sentence_idx": 3,
      "context_window": "($AAPL) by 2.1%, making it their largest holding. This comes as Apple exceeded Q1 earnings expectations, driven by strong iPhone 17 demand, and announced a quarterly dividend of $0.26 per share. Various other institutional investors have also adjusted their positions in AAPL, while analysts have reiterated \"buy\" ratings and raised price targets for the stock.",
      "sentiment_label": "positive",
      "sentiment_score": 0.9505947232246399,
      "positive_score": 0.9505947232246399,
      "negative_score": 0.02331283874809742,
      "neutral_score": 0.026092464104294777
    }
  ],
  "article_sentiment_label": "positive",
  "article_sentiment_score": 0.9531,
  "company_sentiments": {
    "Apple": {
      "label": "positive",
      "score": 0.9536146819591522,
      "positive_score": 0.9536,
      "negative_score": 0.0178,
      "neutral_score": 0.0286,
      "mentions": 2
    },
    "Solidarity Wealth": {
      "label": "positive",
      "score": 0.9546487331390381,
      "positive_score": 0.9546,
      "negative_score": 0.0182,
      "neutral_score": 0.0272,
      "mentions": 1
    },
    "Aa": {
      "label": "positive",
      "score": 0.9505947232246399,
      "positive_score": 0.9506,
      "negative_score": 0.0233,
      "neutral_score": 0.0261,
      "mentions": 1
    }
  },
  "embedding_id": "c4392caf-463d-4146-89cb-b87fd918fadd"
}